odoo10_addon_base_manifest_extension-10.0.1.0.0-py2.7-nspkg.pth
odoo/addons/base_manifest_extension/README.rst
odoo/addons/base_manifest_extension/__init__.py
odoo/addons/base_manifest_extension/__manifest__.py
odoo/addons/base_manifest_extension/hooks.py
odoo/addons/base_manifest_extension/static/description/icon.png
odoo/addons/base_manifest_extension/tests/__init__.py
odoo/addons/base_manifest_extension/tests/test_hooks.py
odoo10_addon_base_manifest_extension-10.0.1.0.0.dist-info/DESCRIPTION.rst
odoo10_addon_base_manifest_extension-10.0.1.0.0.dist-info/METADATA
odoo10_addon_base_manifest_extension-10.0.1.0.0.dist-info/RECORD
odoo10_addon_base_manifest_extension-10.0.1.0.0.dist-info/WHEEL
odoo10_addon_base_manifest_extension-10.0.1.0.0.dist-info/metadata.json
odoo10_addon_base_manifest_extension-10.0.1.0.0.dist-info/namespace_packages.txt
odoo10_addon_base_manifest_extension-10.0.1.0.0.dist-info/top_level.txt
